generics_package_mudit/__init__.py
generics_package_mudit/generics.py
generics_package_mudit-0.1.0.dist-info/LICENSE
generics_package_mudit-0.1.0.dist-info/METADATA
generics_package_mudit-0.1.0.dist-info/WHEEL
generics_package_mudit-0.1.0.dist-info/top_level.txt
generics_package_mudit-0.1.0.dist-info/RECORD
