Metadata-Version: 2.1
Name: generics-package-mudit
Version: 0.1.0
Summary: Generics Package
Author-email: Mudit Sharma <mudit@sopeonow.one>
Classifier: Programming Language :: Python :: 3
Classifier: License :: OSI Approved :: MIT License
Classifier: Operating System :: OS Independent
Requires-Python: >=3.8
License-File: LICENSE
